pulm/__init__.py
pulm/__main__.py
pulm/pulm.py
pulm-0.2.1.dist-info/LICENSE
pulm-0.2.1.dist-info/METADATA
pulm-0.2.1.dist-info/WHEEL
pulm-0.2.1.dist-info/entry_points.txt
pulm-0.2.1.dist-info/top_level.txt
pulm-0.2.1.dist-info/RECORD
