Metadata-Version: 2.1
Name: pulm
Version: 0.2.1
Summary: PlantUML script generator
Home-page: https://github.com/jjerphan/pulm
Author: Julien Jerphanion
Author-email: git@jjerphan.xyz
License: UNKNOWN
Platform: UNKNOWN
Classifier: Programming Language :: Python :: 3
Classifier: License :: OSI Approved :: MIT License
Classifier: Operating System :: OS Independent
